fsmedhro_core/__init__.py
fsmedhro_core/admin.py
fsmedhro_core/api.py
fsmedhro_core/apps.py
fsmedhro_core/forms.py
fsmedhro_core/models.py
fsmedhro_core/urls.py
fsmedhro_core/views.py
fsmedhro_core/backends/auth.py
fsmedhro_core/migrations/0001_initial.py
fsmedhro_core/migrations/0002_alter_field_user_on_fachschaftuser.py
fsmedhro_core/migrations/0003_auto_20201107_2321.py
fsmedhro_core/migrations/0004_auto_20240304_0915.py
fsmedhro_core/migrations/__init__.py
fsmedhro_core/templates/fsmedhro_core/kontaktdaten_add.html
fsmedhro_core/templates/fsmedhro_core/kontaktdaten_list.html
fsmedhro_core/templates/fsmedhro_core/rundmail.html
fsmedhro_core/templates/fsmedhro_core/user_detail.html
fsmedhro_core/templates/fsmedhro_core/user_edit.html
django_fsmedhro_core-0.3.1.dist-info/LICENSE
django_fsmedhro_core-0.3.1.dist-info/METADATA
django_fsmedhro_core-0.3.1.dist-info/WHEEL
django_fsmedhro_core-0.3.1.dist-info/top_level.txt
django_fsmedhro_core-0.3.1.dist-info/RECORD
