Metadata-Version: 2.1
Name: django-fsmedhro-core
Version: 0.3.1
Summary: Basisapp für die Webseite des FSR Medizin der Uni Rostock
Home-page: https://github.com/hutchison/django-fsmedhro-core
Author: Martin Darmüntzel
Author-email: martin@trivialanalog.de
License: MIT License
Classifier: Environment :: Web Environment
Classifier: Framework :: Django
Classifier: Framework :: Django :: 3.1
Classifier: Intended Audience :: Developers
Classifier: License :: OSI Approved :: MIT License
Classifier: Operating System :: OS Independent
Classifier: Programming Language :: Python
Classifier: Programming Language :: Python :: 3.9
Classifier: Topic :: Internet :: WWW/HTTP
Classifier: Topic :: Internet :: WWW/HTTP :: Dynamic Content
Requires-Python: >=3.9
License-File: LICENSE
Requires-Dist: Django >=3.1
Requires-Dist: django-crispy-forms
Requires-Dist: ldap3 >=2.6
Requires-Dist: djangorestframework
